log_colorizer/__init__.py
log_colorizer_k-2.0.0.dist-info/LICENSE
log_colorizer_k-2.0.0.dist-info/METADATA
log_colorizer_k-2.0.0.dist-info/WHEEL
log_colorizer_k-2.0.0.dist-info/top_level.txt
log_colorizer_k-2.0.0.dist-info/RECORD
